vedro_advanced_tags/__init__.py
vedro_advanced_tags/_grammar.py
vedro_advanced_tags/_tag_matcher.py
vedro_advanced_tags/_vedro_advanced_tags.py
vedro_advanced_tags/py.typed
vedro_advanced_tags-0.2.1.dist-info/LICENSE
vedro_advanced_tags-0.2.1.dist-info/METADATA
vedro_advanced_tags-0.2.1.dist-info/WHEEL
vedro_advanced_tags-0.2.1.dist-info/top_level.txt
vedro_advanced_tags-0.2.1.dist-info/RECORD
