Metadata-Version: 2.1
Name: vedro-advanced-tags
Version: 0.2.1
Summary: Vedro tags with boolean logic
Home-page: https://github.com/vedro-universe/vedro-advanced-tags
Author: Nikita Tsvetkov
Author-email: tsv1@fastmail.com
License: Apache-2.0
Classifier: License :: OSI Approved :: Apache Software License
Classifier: Programming Language :: Python :: 3.8
Classifier: Programming Language :: Python :: 3.9
Classifier: Programming Language :: Python :: 3.10
Classifier: Programming Language :: Python :: 3.11
Classifier: Typing :: Typed
Requires-Python: >=3.8
License-File: LICENSE
Requires-Dist: vedro<2.0,>=1.8.3
Requires-Dist: pyparsing<4.0,>=3.0
